petmagotchi/__init__.py
petmagotchi/__main__.py
petmagotchi/pet.py
petmagotchi-0.1.4.dist-info/LICENSE
petmagotchi-0.1.4.dist-info/METADATA
petmagotchi-0.1.4.dist-info/WHEEL
petmagotchi-0.1.4.dist-info/entry_points.txt
petmagotchi-0.1.4.dist-info/top_level.txt
petmagotchi-0.1.4.dist-info/RECORD
