Metadata-Version: 2.1
Name: petmagotchi
Version: 0.1.4
Summary: A fun Tamagotchi and pet simulation package!
Author-email: Capks <capks@placeholder.com>, Allyson <abc9295@nyu.edu>
License: GNU GENERAL PUBLIC LICENSE
Project-URL: Homepage, https://github.com/software-students-fall2023/3-python-package-exercise-leftovers3
Project-URL: Repository, https://github.com/software-students-fall2023/3-python-package-exercise-leftovers3.git
Project-URL: Bug Tracker, https://github.com/software-students-fall2023/3-python-package-exercise-leftovers3/issues
Keywords: python,pet,simulation,virtual pet,tamagotchi
Classifier: Programming Language :: Python :: 3
Classifier: Intended Audience :: Developers
Classifier: License :: OSI Approved :: GNU General Public License v3 (GPLv3)
Classifier: Operating System :: OS Independent
Requires-Python: >=3.7
License-File: LICENSE
Provides-Extra: dev
Requires-Dist: pytest ; extra == 'dev'
